lexsi_sdk/__init__.py
lexsi_sdk/version.py
lexsi_sdk/client/__init__.py
lexsi_sdk/client/client.py
lexsi_sdk/common/__init__.py
lexsi_sdk/common/constants.py
lexsi_sdk/common/enums.py
lexsi_sdk/common/environment.py
lexsi_sdk/common/monitoring.py
lexsi_sdk/common/trigger.py
lexsi_sdk/common/types.py
lexsi_sdk/common/utils.py
lexsi_sdk/common/validation.py
lexsi_sdk/common/xai_uris.py
lexsi_sdk/common/config/.env.prod
lexsi_sdk/core/__init__.py
lexsi_sdk/core/agent.py
lexsi_sdk/core/alert.py
lexsi_sdk/core/case.py
lexsi_sdk/core/dashboard.py
lexsi_sdk/core/lexsi.py
lexsi_sdk/core/model_summary.py
lexsi_sdk/core/organization.py
lexsi_sdk/core/project.py
lexsi_sdk/core/synthetic.py
lexsi_sdk/core/text.py
lexsi_sdk/core/tracer.py
lexsi_sdk/core/utils.py
lexsi_sdk/core/workspace.py
lexsi_sdk/core/wrapper.py
lexsi_sdk/core/xai.py
lexsi_sdk/core/guardrails/__init__.py
lexsi_sdk/core/guardrails/guard_template.py
lexsi_sdk/core/guardrails/guardrail_autogen.py
lexsi_sdk/core/guardrails/guardrails_langgraph.py
lexsi_sdk/core/guardrails/guardrails_openai.py
lexsi_sdk/core/guardrails/openai_runner.py
lexsi_sdk-0.1.26.dist-info/METADATA
lexsi_sdk-0.1.26.dist-info/WHEEL
lexsi_sdk-0.1.26.dist-info/top_level.txt
lexsi_sdk-0.1.26.dist-info/RECORD
